Metadata-Version: 2.1
Name: lgtm-art
Version: 1.0.5
Summary: UNKNOWN
Home-page: UNKNOWN
License: UNKNOWN
Download-URL: https://github.com/Steeeephen/LGTM-Art/archive/refs/tags/1.0.5.tar.gz
Platform: UNKNOWN
